{"State": "Andhra Pradesh", "AC_Name": "Vinukonda", "AC_Number": "99", "Result": [{"Candidate": "Gonuguntla Venkata Seeta Ramnjaneyulu", "Party": "Telugu Desam", "EVM Votes": 91607, "Postal Votes": 468, "Total Votes": 92075, "Percentage of Votes": 41.16}, {"Candidate": "Nalabothu Venkata Rao", "Party": "Bharatiya Janata Party", "EVM Votes": 921, "Postal Votes": 10, "Total Votes": 931, "Percentage of Votes": 0.42}, {"Candidate": "Bolla Brahma Naidu", "Party": "Yuvajana Sramika Rythu Congress Party", "EVM Votes": 119811, "Postal Votes": 892, "Total Votes": 120703, "Percentage of Votes": 53.96}, {"Candidate": "Vijay Kumar Atluri", "Party": "Indian National Congress", "EVM Votes": 1924, "Postal Votes": 1, "Total Votes": 1925, "Percentage of Votes": 0.86}, {"Candidate": "Gaddam Ramana", "Party": "Pyramid Party of India", "EVM Votes": 198, "Postal Votes": 3, "Total Votes": 201, "Percentage of Votes": 0.09}, {"Candidate": "Chenna SrinivasaRao", "Party": "Janasena Party", "EVM Votes": 4598, "Postal Votes": 39, "Total Votes": 4637, "Percentage of Votes": 2.07}, {"Candidate": "Janapati Parameswararao", "Party": "Samajwadi Party", "EVM Votes": 110, "Postal Votes": 0, "Total Votes": 110, "Percentage of Votes": 0.05}, {"Candidate": "Medikonda Lakshmi KanthaRao", "Party": "Navarang Congress Party", "EVM Votes": 76, "Postal Votes": 0, "Total Votes": 76, "Percentage of Votes": 0.03}, {"Candidate": "Batchu Venkata Ravi Kumar", "Party": "Navataram Party", "EVM Votes": 54, "Postal Votes": 0, "Total Votes": 54, "Percentage of Votes": 0.02}, {"Candidate": "Ustala China Kasaiah", "Party": "Independent", "EVM Votes": 110, "Postal Votes": 0, "Total Votes": 110, "Percentage of Votes": 0.05}, {"Candidate": "Gangineni Brahmanaidu", "Party": "Independent", "EVM Votes": 168, "Postal Votes": 1, "Total Votes": 169, "Percentage of Votes": 0.08}, {"Candidate": "Pasam Naga Malleswararao", "Party": "Independent", "EVM Votes": 241, "Postal Votes": 0, "Total Votes": 241, "Percentage of Votes": 0.11}, {"Candidate": "Manda VenkatRao", "Party": "Independent", "EVM Votes": 503, "Postal Votes": 0, "Total Votes": 503, "Percentage of Votes": 0.22}, {"Candidate": "NOTA", "Party": "None of the Above", "EVM Votes": 1939, "Postal Votes": 3, "Total Votes": 1942, "Percentage of Votes": 0.87}], "Voters": {"EVM Voters": 222260, "Postal Voters": 1417, "Total Voters": 223677}, "Year": 2019}