{"State": "Uttar Pradesh", "PC_Name": "Ballia", "PC_Number": "72", "Result": [{"Candidate": "Virendra Singh", "Party": "Bharatiya Janata Party", "EVM Votes": 464039, "Postal Votes": 5075, "Total Votes": 469114, "Percentage of Votes": 47.4}, {"Candidate": "Sanatan Pandey", "Party": "Samajwadi Party", "EVM Votes": 450408, "Postal Votes": 3187, "Total Votes": 453595, "Percentage of Votes": 45.83}, {"Candidate": "ARVIND", "Party": "Bhartiya Jan Nayak Party", "EVM Votes": 3895, "Postal Votes": 130, "Total Votes": 4025, "Percentage of Votes": 0.41}, {"Candidate": "Uday Prakash", "Party": "Janta Raj Party", "EVM Votes": 1352, "Postal Votes": 7, "Total Votes": 1359, "Percentage of Votes": 0.14}, {"Candidate": "GOPAL RAM KHARWAR", "Party": "Gondvana Gantantra Party", "EVM Votes": 3950, "Postal Votes": 52, "Total Votes": 4002, "Percentage of Votes": 0.4}, {"Candidate": "Janmejay Kumar Prajapati", "Party": "Bharatiya Samta Samaj Party", "EVM Votes": 2442, "Postal Votes": 12, "Total Votes": 2454, "Percentage of Votes": 0.25}, {"Candidate": "Vinod", "Party": "Suheldev Bharatiya Samaj Party", "EVM Votes": 35874, "Postal Votes": 26, "Total Votes": 35900, "Percentage of Votes": 3.63}, {"Candidate": "Seema Chauhan", "Party": "Janta Kranti Party (Rashtravadi)", "EVM Votes": 2409, "Postal Votes": 44, "Total Votes": 2453, "Percentage of Votes": 0.25}, {"Candidate": "OM PRAKASH PANDEY", "Party": "Independent", "EVM Votes": 1768, "Postal Votes": 7, "Total Votes": 1775, "Percentage of Votes": 0.18}, {"Candidate": "Major Ramesh Chandra Upadhyay", "Party": "Independent", "EVM Votes": 5435, "Postal Votes": 5, "Total Votes": 5440, "Percentage of Votes": 0.55}, {"Candidate": "NOTA", "Party": "None of the Above", "EVM Votes": 9540, "Postal Votes": 75, "Total Votes": 9615, "Percentage of Votes": 0.97}], "Voters": {"EVM Voters": 981112, "Postal Voters": 8620, "Total Voters": 989732}, "Year": 2019}