{"State": "Uttar Pradesh", "PC_Name": "Barabanki", "PC_Number": "53", "Result": [{"Candidate": "Upendra Singh Rawat", "Party": "Bharatiya Janata Party", "EVM Votes": 535594, "Postal Votes": 323, "Total Votes": 535917, "Percentage of Votes": 46.39}, {"Candidate": "Tanuj Punia", "Party": "Indian National Congress", "EVM Votes": 159575, "Postal Votes": 36, "Total Votes": 159611, "Percentage of Votes": 13.82}, {"Candidate": "Ram Sagar Rawat", "Party": "Samajwadi Party", "EVM Votes": 425624, "Postal Votes": 153, "Total Votes": 425777, "Percentage of Votes": 36.85}, {"Candidate": "Asha Devi", "Party": "Lok Dal", "EVM Votes": 5761, "Postal Votes": 1, "Total Votes": 5762, "Percentage of Votes": 0.5}, {"Candidate": "Om kar", "Party": "Bahujan Mukti Party", "EVM Votes": 1369, "Postal Votes": 2, "Total Votes": 1371, "Percentage of Votes": 0.12}, {"Candidate": "Kalpana Rawat", "Party": "Bharat Prabhat Party", "EVM Votes": 1048, "Postal Votes": 1, "Total Votes": 1049, "Percentage of Votes": 0.09}, {"Candidate": "Tarawati", "Party": "Awami Samta Party", "EVM Votes": 1920, "Postal Votes": 1, "Total Votes": 1921, "Percentage of Votes": 0.17}, {"Candidate": "Fool Dulari", "Party": "Samdarshi Samaj Party", "EVM Votes": 1622, "Postal Votes": 2, "Total Votes": 1624, "Percentage of Votes": 0.14}, {"Candidate": "Vinod Kumar", "Party": "Aam Janta Party (India)", "EVM Votes": 1622, "Postal Votes": 0, "Total Votes": 1622, "Percentage of Votes": 0.14}, {"Candidate": "Santosh Kumari", "Party": "Dr. Bhimrao Ambedkar Dal", "EVM Votes": 1549, "Postal Votes": 0, "Total Votes": 1549, "Percentage of Votes": 0.13}, {"Candidate": "Kishan Lal", "Party": "Independent", "EVM Votes": 2288, "Postal Votes": 1, "Total Votes": 2289, "Percentage of Votes": 0.2}, {"Candidate": "Molhey Ram Rawat", "Party": "Independent", "EVM Votes": 4380, "Postal Votes": 1, "Total Votes": 4381, "Percentage of Votes": 0.38}, {"Candidate": "Manju Devi", "Party": "Independent", "EVM Votes": 3683, "Postal Votes": 0, "Total Votes": 3683, "Percentage of Votes": 0.32}, {"Candidate": "NOTA", "Party": "None of the Above", "EVM Votes": 8783, "Postal Votes": 2, "Total Votes": 8785, "Percentage of Votes": 0.76}], "Voters": {"EVM Voters": 1154818, "Postal Voters": 523, "Total Voters": 1155341}, "Year": 2019}