{"State": "Uttar Pradesh", "PC_Name": "Etawah", "PC_Number": "41", "Result": [{"Candidate": "ASHOK KUMAR DOHARE", "Party": "Indian National Congress", "EVM Votes": 16460, "Postal Votes": 110, "Total Votes": 16570, "Percentage of Votes": 1.61}, {"Candidate": "KAMLESH KUMAR", "Party": "Samajwadi Party", "EVM Votes": 455957, "Postal Votes": 1725, "Total Votes": 457682, "Percentage of Votes": 44.53}, {"Candidate": "Dr RAM SHANKAR KATHERIA", "Party": "Bharatiya Janata Party", "EVM Votes": 519674, "Postal Votes": 2445, "Total Votes": 522119, "Percentage of Votes": 50.8}, {"Candidate": "AKSHASH KRISHNA", "Party": "Pichhra Samaj Party", "EVM Votes": 4064, "Postal Votes": 9, "Total Votes": 4073, "Percentage of Votes": 0.4}, {"Candidate": "AJAY KUMAR", "Party": "Bhartiya Jan Nayak Party", "EVM Votes": 850, "Postal Votes": 5, "Total Votes": 855, "Percentage of Votes": 0.08}, {"Candidate": "ARUN KUMAR", "Party": "Jan Samman party", "EVM Votes": 837, "Postal Votes": 3, "Total Votes": 840, "Percentage of Votes": 0.08}, {"Candidate": "ARTI DEVI", "Party": "Mahasankalp Janta Party", "EVM Votes": 1481, "Postal Votes": 12, "Total Votes": 1493, "Percentage of Votes": 0.15}, {"Candidate": "LALTA PRASAD", "Party": "Voters Party  International", "EVM Votes": 1265, "Postal Votes": 1, "Total Votes": 1266, "Percentage of Votes": 0.12}, {"Candidate": "SHAMBHU DAYAL DOHARE", "Party": "Pragatishil Samajwadi Party (Lohia)", "EVM Votes": 8657, "Postal Votes": 18, "Total Votes": 8675, "Percentage of Votes": 0.84}, {"Candidate": "SITA", "Party": "Bhartiya Shakti Chetna Party", "EVM Votes": 1153, "Postal Votes": 1, "Total Votes": 1154, "Percentage of Votes": 0.11}, {"Candidate": "DALVEER SINGH", "Party": "Independent", "EVM Votes": 2111, "Postal Votes": 1, "Total Votes": 2112, "Percentage of Votes": 0.21}, {"Candidate": "POOJA", "Party": "Independent", "EVM Votes": 2504, "Postal Votes": 4, "Total Votes": 2508, "Percentage of Votes": 0.24}, {"Candidate": "SANJAY KUMAR", "Party": "Independent", "EVM Votes": 2857, "Postal Votes": 1, "Total Votes": 2858, "Percentage of Votes": 0.28}, {"Candidate": "NOTA", "Party": "None of the Above", "EVM Votes": 5580, "Postal Votes": 30, "Total Votes": 5610, "Percentage of Votes": 0.55}], "Voters": {"EVM Voters": 1023450, "Postal Voters": 4365, "Total Voters": 1027815}, "Year": 2019}