{"State": "Uttar Pradesh", "PC_Name": "Mathura", "PC_Number": "17", "Result": [{"Candidate": "KUNWAR NARENDRA SINGH", "Party": "Rashtriya Lok Dal", "EVM Votes": 377319, "Postal Votes": 503, "Total Votes": 377822, "Percentage of Votes": 34.26}, {"Candidate": "MAHESH PATHAK", "Party": "Indian National Congress", "EVM Votes": 27970, "Postal Votes": 114, "Total Votes": 28084, "Percentage of Votes": 2.55}, {"Candidate": "HEMA MALINI", "Party": "Bharatiya Janata Party", "EVM Votes": 667342, "Postal Votes": 3951, "Total Votes": 671293, "Percentage of Votes": 60.88}, {"Candidate": "OMPRAKASH", "Party": "Swatantra Jantaraj Party", "EVM Votes": 5090, "Postal Votes": 5, "Total Votes": 5095, "Percentage of Votes": 0.46}, {"Candidate": "CHATTAR alias CHATRAPAL SINGH NISHAD", "Party": "Bahujan Mukti Party", "EVM Votes": 780, "Postal Votes": 14, "Total Votes": 794, "Percentage of Votes": 0.07}, {"Candidate": "JAGVIR SINGH", "Party": "Pragatishil Samajwadi Party (Lohia)", "EVM Votes": 467, "Postal Votes": 3, "Total Votes": 470, "Percentage of Votes": 0.04}, {"Candidate": "JASVANT SINGH BAGHEL", "Party": "Rashtriya Shoshit Samaj Party", "EVM Votes": 1240, "Postal Votes": 5, "Total Votes": 1245, "Percentage of Votes": 0.11}, {"Candidate": "JASVEER SINGH", "Party": "Rashtriya Naujawan Dal", "EVM Votes": 1628, "Postal Votes": 2, "Total Votes": 1630, "Percentage of Votes": 0.15}, {"Candidate": "DINESH GAUTAM", "Party": "Bhartiya Anarakshit Party", "EVM Votes": 2360, "Postal Votes": 3, "Total Votes": 2363, "Percentage of Votes": 0.21}, {"Candidate": "RAMDEV GAUTAM", "Party": "Bhartiya Lok Seva Dal", "EVM Votes": 1260, "Postal Votes": 1, "Total Votes": 1261, "Percentage of Votes": 0.11}, {"Candidate": "PRAMOD KRISHNA", "Party": "Independent", "EVM Votes": 1489, "Postal Votes": 1, "Total Votes": 1490, "Percentage of Votes": 0.14}, {"Candidate": "PHAKKAD BABA", "Party": "Independent", "EVM Votes": 4084, "Postal Votes": 2, "Total Votes": 4086, "Percentage of Votes": 0.37}, {"Candidate": "RAMDAS TYAGI", "Party": "Independent", "EVM Votes": 1295, "Postal Votes": 3, "Total Votes": 1298, "Percentage of Votes": 0.12}, {"Candidate": "NOTA", "Party": "None of the Above", "EVM Votes": 5788, "Postal Votes": 12, "Total Votes": 5800, "Percentage of Votes": 0.53}], "Voters": {"EVM Voters": 1098112, "Postal Voters": 4619, "Total Voters": 1102731}, "Year": 2019}