{"State": "Maharashtra", "PC_Name": "Shirur", "PC_Number": "36", "Result": [{"Candidate": "Adhalrao Shivaji Dattatrey", "Party": "Shivsena", "EVM Votes": 576002, "Postal Votes": 1345, "Total Votes": 577347, "Percentage of Votes": 44.65}, {"Candidate": "Dr. Amol Ramsing Kolhe", "Party": "Nationalist Congress Party", "EVM Votes": 634554, "Postal Votes": 1276, "Total Votes": 635830, "Percentage of Votes": 49.17}, {"Candidate": "Kagadi Jamirkhan Afjal", "Party": "Bahujan Samaj Party", "EVM Votes": 7239, "Postal Votes": 8, "Total Votes": 7247, "Percentage of Votes": 0.56}, {"Candidate": "Ovhal Rahul", "Party": "Vanchit Bahujan Aaghadi", "EVM Votes": 38028, "Postal Votes": 42, "Total Votes": 38070, "Percentage of Votes": 2.94}, {"Candidate": "Ghare Mohan Damodar", "Party": "Baliraja Party", "EVM Votes": 996, "Postal Votes": 1, "Total Votes": 997, "Percentage of Votes": 0.08}, {"Candidate": "Nitin Murlidhar Kuchekar", "Party": "Bharat Prabhat Party", "EVM Votes": 604, "Postal Votes": 3, "Total Votes": 607, "Percentage of Votes": 0.05}, {"Candidate": "Shashikant Rajaram Desai", "Party": "Independent", "EVM Votes": 1880, "Postal Votes": 1, "Total Votes": 1881, "Percentage of Votes": 0.15}, {"Candidate": "Somnath Hiraman Mali", "Party": "Bahujan Republican  Socialist Party", "EVM Votes": 741, "Postal Votes": 2, "Total Votes": 743, "Percentage of Votes": 0.06}, {"Candidate": "Sanjay Baba Bansode", "Party": "BhartiyaBahujanKranti Dal", "EVM Votes": 615, "Postal Votes": 0, "Total Votes": 615, "Percentage of Votes": 0.05}, {"Candidate": "Sanjay Laxman Padwal", "Party": "Bhartiya Navjawan Sena (Paksha)", "EVM Votes": 627, "Postal Votes": 3, "Total Votes": 630, "Percentage of Votes": 0.05}, {"Candidate": "Prof.Shrikant Nivrutti Chabukswar Sir", "Party": "Bahujan Mukti Party", "EVM Votes": 1241, "Postal Votes": 2, "Total Votes": 1243, "Percentage of Votes": 0.1}, {"Candidate": "Ansari Samshad Anwar", "Party": "Independent", "EVM Votes": 826, "Postal Votes": 2, "Total Votes": 828, "Percentage of Votes": 0.06}, {"Candidate": "Ashtul Vikas Rajaram", "Party": "Independent", "EVM Votes": 786, "Postal Votes": 0, "Total Votes": 786, "Percentage of Votes": 0.06}, {"Candidate": "Gangadhar Nathu Yadav", "Party": "Independent", "EVM Votes": 955, "Postal Votes": 0, "Total Votes": 955, "Percentage of Votes": 0.07}, {"Candidate": "Ghadge Balasaheb Jaysing", "Party": "Independent", "EVM Votes": 2749, "Postal Votes": 0, "Total Votes": 2749, "Percentage of Votes": 0.21}, {"Candidate": "Chhaya Prabhakar Solanke", "Party": "Independent", "EVM Votes": 4925, "Postal Votes": 5, "Total Votes": 4930, "Percentage of Votes": 0.38}, {"Candidate": "Bhausaheb Ramchandra Adagale", "Party": "Independent", "EVM Votes": 4397, "Postal Votes": 0, "Total Votes": 4397, "Percentage of Votes": 0.34}, {"Candidate": "Waheeda Shainur Shaikh", "Party": "Independent", "EVM Votes": 3836, "Postal Votes": 1, "Total Votes": 3837, "Percentage of Votes": 0.3}, {"Candidate": "Vinod Vasant Chandgude", "Party": "Independent", "EVM Votes": 901, "Postal Votes": 1, "Total Votes": 902, "Percentage of Votes": 0.07}, {"Candidate": "Shahid Farukh Shaikh", "Party": "Independent", "EVM Votes": 566, "Postal Votes": 0, "Total Votes": 566, "Percentage of Votes": 0.04}, {"Candidate": "Shivajirao Uttamrao Pawar", "Party": "Independent", "EVM Votes": 670, "Postal Votes": 3, "Total Votes": 673, "Percentage of Votes": 0.05}, {"Candidate": "Shaikh Raisa", "Party": "Bhartiya Kisan Party", "EVM Votes": 555, "Postal Votes": 1, "Total Votes": 556, "Percentage of Votes": 0.04}, {"Candidate": "Sonalitai Thorat", "Party": "Independent", "EVM Votes": 676, "Postal Votes": 1, "Total Votes": 677, "Percentage of Votes": 0.05}, {"Candidate": "NOTA", "Party": "None of the Above", "EVM Votes": 6026, "Postal Votes": 25, "Total Votes": 6051, "Percentage of Votes": 0.47}], "Voters": {"EVM Voters": 1290395, "Postal Voters": 2722, "Total Voters": 1293117}, "Year": 2019}