{"State": "Goa", "AC_Name": "Panaji", "AC_Number": "11", "Result": [{"Candidate": "Atanasio Monserrate", "Party": "Indian National Congress", "EVM Votes": 8748, "Postal Votes": 0, "Total Votes": 8748, "Percentage of Votes": 51.71}, {"Candidate": "Sidharth Sripad Kuncalienker", "Party": "Bharatiya Janata Party", "EVM Votes": 6990, "Postal Votes": 0, "Total Votes": 6990, "Percentage of Votes": 41.32}, {"Candidate": "Subhash Bhaskar Velingkar", "Party": "Goa Suraksha Manch", "EVM Votes": 516, "Postal Votes": 0, "Total Votes": 516, "Percentage of Votes": 3.05}, {"Candidate": "Valmiki Naik", "Party": "Aam Aadmi Party", "EVM Votes": 436, "Postal Votes": 0, "Total Votes": 436, "Percentage of Votes": 2.58}, {"Candidate": "Dilip Kashinath Ghadi", "Party": "Independent", "EVM Votes": 13, "Postal Votes": 0, "Total Votes": 13, "Percentage of Votes": 0.08}, {"Candidate": "Vijay More", "Party": "Independent", "EVM Votes": 13, "Postal Votes": 0, "Total Votes": 13, "Percentage of Votes": 0.08}, {"Candidate": "NOTA", "Party": "None of the Above", "EVM Votes": 202, "Postal Votes": 0, "Total Votes": 202, "Percentage of Votes": 1.19}], "Voters": {"EVM Voters": 16918, "Postal Voters": 0, "Total Voters": 16918}, "Year": 2019}