{"State": "Odisha", "AC_Name": "Karanjia", "AC_Number": "30", "Result": [{"Candidate": "JABAMANI TUDU", "Party": "All India Trinamool Congress", "EVM Votes": 6010, "Postal Votes": 3, "Total Votes": 6013, "Percentage of Votes": 4.27}, {"Candidate": "PADMA CHARAN HAIBURU", "Party": "Bharatiya Janata Party", "EVM Votes": 51177, "Postal Votes": 124, "Total Votes": 51301, "Percentage of Votes": 36.43}, {"Candidate": "BASANTI HEMBRAM", "Party": "Biju Janata Dal", "EVM Votes": 60030, "Postal Votes": 34, "Total Votes": 60064, "Percentage of Votes": 42.65}, {"Candidate": "SUDAM CHARAN NAIK", "Party": "Indian National Congress", "EVM Votes": 10837, "Postal Votes": 3, "Total Votes": 10840, "Percentage of Votes": 7.7}, {"Candidate": "BAJURAM SIDU", "Party": "SOCIALIST UNITY CENTRE OF INDIA (COMMUNIST)", "EVM Votes": 3672, "Postal Votes": 1, "Total Votes": 3673, "Percentage of Votes": 2.61}, {"Candidate": "RAGHUNATH NAYAK", "Party": "Akhil Bharat Hindu Mahasabha", "EVM Votes": 1161, "Postal Votes": 0, "Total Votes": 1161, "Percentage of Votes": 0.82}, {"Candidate": "BAIDYANATH SING", "Party": "Independent", "EVM Votes": 1204, "Postal Votes": 0, "Total Votes": 1204, "Percentage of Votes": 0.85}, {"Candidate": "SAMAI CHARAN PURTY", "Party": "Independent", "EVM Votes": 2400, "Postal Votes": 3, "Total Votes": 2403, "Percentage of Votes": 1.71}, {"Candidate": "SUJIT KUMAR LUGUN", "Party": "Independent", "EVM Votes": 1110, "Postal Votes": 0, "Total Votes": 1110, "Percentage of Votes": 0.79}, {"Candidate": "SUBASH CHANDRA HEMBRAM", "Party": "Independent", "EVM Votes": 1070, "Postal Votes": 0, "Total Votes": 1070, "Percentage of Votes": 0.76}, {"Candidate": "NOTA", "Party": "None of the Above", "EVM Votes": 1989, "Postal Votes": 0, "Total Votes": 1989, "Percentage of Votes": 1.41}], "Voters": {"EVM Voters": 140660, "Postal Voters": 168, "Total Voters": 140828}, "Year": 2019}