{"State": "Odisha", "AC_Name": "Nayagarh", "AC_Number": "122", "Result": [{"Candidate": "Aruna Kumar Sahoo", "Party": "Biju Janata Dal", "EVM Votes": 81548, "Postal Votes": 44, "Total Votes": 81592, "Percentage of Votes": 52.41}, {"Candidate": "Irani Ray", "Party": "Bharatiya Janata Party", "EVM Votes": 66600, "Postal Votes": 137, "Total Votes": 66737, "Percentage of Votes": 42.87}, {"Candidate": "Manoj Kumar Sahoo", "Party": "Indian National Congress", "EVM Votes": 4221, "Postal Votes": 8, "Total Votes": 4229, "Percentage of Votes": 2.72}, {"Candidate": "Subhalaxmi Dash", "Party": "Ambedkar National Congress", "EVM Votes": 594, "Postal Votes": 3, "Total Votes": 597, "Percentage of Votes": 0.38}, {"Candidate": "Giridhari Rout", "Party": "Independent", "EVM Votes": 418, "Postal Votes": 0, "Total Votes": 418, "Percentage of Votes": 0.27}, {"Candidate": "Balaram Sahoo", "Party": "Independent", "EVM Votes": 446, "Postal Votes": 0, "Total Votes": 446, "Percentage of Votes": 0.29}, {"Candidate": "Srikanta Dash", "Party": "Independent", "EVM Votes": 345, "Postal Votes": 0, "Total Votes": 345, "Percentage of Votes": 0.22}, {"Candidate": "Hemanta Kumar Prusty", "Party": "Independent", "EVM Votes": 408, "Postal Votes": 0, "Total Votes": 408, "Percentage of Votes": 0.26}, {"Candidate": "NOTA", "Party": "None of the Above", "EVM Votes": 916, "Postal Votes": 0, "Total Votes": 916, "Percentage of Votes": 0.59}], "Voters": {"EVM Voters": 155496, "Postal Voters": 192, "Total Voters": 155688}, "Year": 2019}