[{"State": "NCT OF Delhi", "PC_Name": "CHANDNI CHOWK", "PC_Number": "1", "Result": [{"Candidate": "JAI PRAKASH AGARWAL", "Party": "Indian National Congress", "EVM Votes": 290689, "Postal Votes": 221, "Total Votes": 290910, "Percentage of Votes": 29.67}, {"Candidate": "PANKAJ KUMAR GUPTA", "Party": "Aam Aadmi Party", "EVM Votes": 144447, "Postal Votes": 104, "Total Votes": 144551, "Percentage of Votes": 14.74}, {"Candidate": "SHAHID ALI", "Party": "Bahujan Samaj Party", "EVM Votes": 9013, "Postal Votes": 13, "Total Votes": 9026, "Percentage of Votes": 0.92}, {"Candidate": "HARSH VARDHAN", "Party": "Bharatiya Janata Party", "EVM Votes": 517939, "Postal Votes": 1116, "Total Votes": 519055, "Percentage of Votes": 52.94}, {"Candidate": "ANIL KUMAR", "Party": "Rashtriya Rashtrawadi Party", "EVM Votes": 1436, "Postal Votes": 0, "Total Votes": 1436, "Percentage of Votes": 0.15}, {"Candidate": "ASHOK KUMAR", "Party": "Republican Party of India (A)", "EVM Votes": 273, "Postal Votes": 0, "Total Votes": 273, "Percentage of Votes": 0.03}, {"Candidate": "INDER SEN", "Party": "Rashtriya Samrasta Party", "EVM Votes": 216, "Postal Votes": 0, "Total Votes": 216, "Percentage of Votes": 0.02}, {"Candidate": "MOHD. IRFAN JAVED QURESHI", "Party": "Ekta Samaj Party", "EVM Votes": 1270, "Postal Votes": 0, "Total Votes": 1270, "Percentage of Votes": 0.13}, {"Candidate": "KAMAL KISHOR", "Party": "Peoples Party of India (Democratic)", "EVM Votes": 331, "Postal Votes": 1, "Total Votes": 332, "Percentage of Votes": 0.03}, {"Candidate": "DEEPTI CHOPRA", "Party": "Prism", "EVM Votes": 233, "Postal Votes": 0, "Total Votes": 233, "Percentage of Votes": 0.02}, {"Candidate": "DHEER SINGH", "Party": "Rashtriya Jansambhavna Party", "EVM Votes": 249, "Postal Votes": 0, "Total Votes": 249, "Percentage of Votes": 0.03}, {"Candidate": "RAVINDRA", "Party": "Kanshiram Bahujan Dal", "EVM Votes": 369, "Postal Votes": 0, "Total Votes": 369, "Percentage of Votes": 0.04}, {"Candidate": "RICHA KATIYAR KANAUJIA", "Party": "Right to Recall Party", "EVM Votes": 474, "Postal Votes": 1, "Total Votes": 475, "Percentage of Votes": 0.05}, {"Candidate": "VISHAL KHANNA", "Party": "Sanatan Sanskriti Raksha Dal", "EVM Votes": 485, "Postal Votes": 0, "Total Votes": 485, "Percentage of Votes": 0.05}, {"Candidate": "VIRENDER PRATAP SINGH", "Party": "Aapki Apni Party (Peoples)", "EVM Votes": 741, "Postal Votes": 3, "Total Votes": 744, "Percentage of Votes": 0.08}, {"Candidate": "SHARESTHA ARORA", "Party": "Mazdoor Kirayedar Vikas Party", "EVM Votes": 1143, "Postal Votes": 0, "Total Votes": 1143, "Percentage of Votes": 0.12}, {"Candidate": "SATDEV JAIN", "Party": "Proutist Bloc, India", "EVM Votes": 1215, "Postal Votes": 0, "Total Votes": 1215, "Percentage of Votes": 0.12}, {"Candidate": "SAMEER MIRZA", "Party": "Bharat Prabhat Party", "EVM Votes": 423, "Postal Votes": 1, "Total Votes": 424, "Percentage of Votes": 0.04}, {"Candidate": "SUMAN DEVI", "Party": "Bharat Lok Sewak Party", "EVM Votes": 236, "Postal Votes": 0, "Total Votes": 236, "Percentage of Votes": 0.02}, {"Candidate": "SOHAN LAL SHARMA", "Party": "Rashtra Nirman Party", "EVM Votes": 501, "Postal Votes": 0, "Total Votes": 501, "Percentage of Votes": 0.05}, {"Candidate": "SAURABH RANJAN", "Party": "Pyramid Party of India", "EVM Votes": 243, "Postal Votes": 0, "Total Votes": 243, "Percentage of Votes": 0.02}, {"Candidate": "JUGAL KISHOR", "Party": "Independent", "EVM Votes": 268, "Postal Votes": 0, "Total Votes": 268, "Percentage of Votes": 0.03}, {"Candidate": "PANKAJ GUPTA", "Party": "Independent", "EVM Votes": 670, "Postal Votes": 0, "Total Votes": 670, "Percentage of Votes": 0.07}, {"Candidate": "FARHA DEEBA", "Party": "Independent", "EVM Votes": 241, "Postal Votes": 0, "Total Votes": 241, "Percentage of Votes": 0.02}, {"Candidate": "MUNNA LAL", "Party": "Independent", "EVM Votes": 393, "Postal Votes": 0, "Total Votes": 393, "Percentage of Votes": 0.04}, {"Candidate": "RAVI KUMAR", "Party": "Independent", "EVM Votes": 299, "Postal Votes": 0, "Total Votes": 299, "Percentage of Votes": 0.03}, {"Candidate": "NOTA", "Party": "None of the Above", "EVM Votes": 5124, "Postal Votes": 9, "Total Votes": 5133, "Percentage of Votes": 0.52}], "Voters": {"EVM Voters": 978921, "Postal Voters": 1469, "Total Voters": 980390}, "Year": 2019}, {"State": "NCT OF Delhi", "PC_Name": "EAST DELHI", "PC_Number": "3", "Result": [{"Candidate": "ARVINDER SINGH LOVELY", "Party": "Indian National Congress", "EVM Votes": 304718, "Postal Votes": 216, "Total Votes": 304934, "Percentage of Votes": 24.24}, {"Candidate": "ATISHI", "Party": "Aam Aadmi Party", "EVM Votes": 219156, "Postal Votes": 172, "Total Votes": 219328, "Percentage of Votes": 17.44}, {"Candidate": "GAUTAM GAMBHIR", "Party": "Bharatiya Janata Party", "EVM Votes": 695109, "Postal Votes": 1047, "Total Votes": 696156, "Percentage of Votes": 55.35}, {"Candidate": "SANJAY KUMAR", "Party": "Bahujan Samaj Party", "EVM Votes": 19033, "Postal Votes": 57, "Total Votes": 19090, "Percentage of Votes": 1.52}, {"Candidate": "AJAY CHAUDHARY", "Party": "Aapki Apni Party (Peoples)", "EVM Votes": 1282, "Postal Votes": 0, "Total Votes": 1282, "Percentage of Votes": 0.1}, {"Candidate": "ANUPAM TRIPATHI", "Party": "Bhartiya Kisan Party", "EVM Votes": 288, "Postal Votes": 1, "Total Votes": 289, "Percentage of Votes": 0.02}, {"Candidate": "AMANULLAH AHMED", "Party": "Bhartiya Insan Party", "EVM Votes": 512, "Postal Votes": 0, "Total Votes": 512, "Percentage of Votes": 0.04}, {"Candidate": "DR. KRISHAN SINGH CHAUHAN", "Party": "Peoples Party of India (Democratic)", "EVM Votes": 643, "Postal Votes": 0, "Total Votes": 643, "Percentage of Votes": 0.05}, {"Candidate": "DEEPTI NADELLA", "Party": "Pyramid Party of India", "EVM Votes": 323, "Postal Votes": 0, "Total Votes": 323, "Percentage of Votes": 0.03}, {"Candidate": "D. DURGA PRASAD", "Party": "Challengers Party", "EVM Votes": 274, "Postal Votes": 0, "Total Votes": 274, "Percentage of Votes": 0.02}, {"Candidate": "NEERU MONGIA", "Party": "Prism", "EVM Votes": 255, "Postal Votes": 0, "Total Votes": 255, "Percentage of Votes": 0.02}, {"Candidate": "MUKESH JADLY", "Party": "Uttarakhand Pragatisheel Party", "EVM Votes": 943, "Postal Votes": 0, "Total Votes": 943, "Percentage of Votes": 0.07}, {"Candidate": "MOHAN LAL SHARMA", "Party": "Satya Bahumat Party", "EVM Votes": 352, "Postal Votes": 0, "Total Votes": 352, "Percentage of Votes": 0.03}, {"Candidate": "MANJEET SINGH", "Party": "Rashtra Nirman Party", "EVM Votes": 634, "Postal Votes": 0, "Total Votes": 634, "Percentage of Votes": 0.05}, {"Candidate": "MANJU CHHIBBER", "Party": "Republican Party of India (A)", "EVM Votes": 503, "Postal Votes": 0, "Total Votes": 503, "Percentage of Votes": 0.04}, {"Candidate": "SATISH KUMAR PRAJAPATI", "Party": "Mazdoor Kirayedar Vikas Party", "EVM Votes": 1239, "Postal Votes": 0, "Total Votes": 1239, "Percentage of Votes": 0.1}, {"Candidate": "SURENDER GUPTA", "Party": "National Apni Party", "EVM Votes": 1044, "Postal Votes": 0, "Total Votes": 1044, "Percentage of Votes": 0.08}, {"Candidate": "HAFIZ BURHANUDDIN", "Party": "The National Road Map Party of India", "EVM Votes": 699, "Postal Votes": 0, "Total Votes": 699, "Percentage of Votes": 0.06}, {"Candidate": "HITESH KUMAR", "Party": "Jai Prakash Janata Dal", "EVM Votes": 937, "Postal Votes": 0, "Total Votes": 937, "Percentage of Votes": 0.07}, {"Candidate": "ASHOK SURANA", "Party": "Independent", "EVM Votes": 650, "Postal Votes": 0, "Total Votes": 650, "Percentage of Votes": 0.05}, {"Candidate": "MANOJ KUMAR GUPTA", "Party": "Independent", "EVM Votes": 496, "Postal Votes": 0, "Total Votes": 496, "Percentage of Votes": 0.04}, {"Candidate": "RAVI KUMAR", "Party": "Independent", "EVM Votes": 328, "Postal Votes": 0, "Total Votes": 328, "Percentage of Votes": 0.03}, {"Candidate": "RAHIMUDDIN SHAH", "Party": "Independent", "EVM Votes": 318, "Postal Votes": 0, "Total Votes": 318, "Percentage of Votes": 0.03}, {"Candidate": "RAJ KUMAR DHINGIYA", "Party": "Independent", "EVM Votes": 586, "Postal Votes": 0, "Total Votes": 586, "Percentage of Votes": 0.05}, {"Candidate": "SHIV KUMAR", "Party": "Independent", "EVM Votes": 408, "Postal Votes": 0, "Total Votes": 408, "Percentage of Votes": 0.03}, {"Candidate": "HARBALWINDER SINGH", "Party": "Independent", "EVM Votes": 677, "Postal Votes": 1, "Total Votes": 678, "Percentage of Votes": 0.05}, {"Candidate": "NOTA", "Party": "None of the Above", "EVM Votes": 4907, "Postal Votes": 13, "Total Votes": 4920, "Percentage of Votes": 0.39}], "Voters": {"EVM Voters": 1256314, "Postal Voters": 1507, "Total Voters": 1257821}, "Year": 2019}, {"State": "NCT OF Delhi", "PC_Name": "NEW DELHI", "PC_Number": "4", "Result": [{"Candidate": "AJAY MAKAN", "Party": "Indian National Congress", "EVM Votes": 247429, "Postal Votes": 273, "Total Votes": 247702, "Percentage of Votes": 26.91}, {"Candidate": "BRIJESH GOYAL", "Party": "Aam Aadmi Party", "EVM Votes": 150203, "Postal Votes": 139, "Total Votes": 150342, "Percentage of Votes": 16.33}, {"Candidate": "MEENAKASHI LEKHI", "Party": "Bharatiya Janata Party", "EVM Votes": 503157, "Postal Votes": 1049, "Total Votes": 504206, "Percentage of Votes": 54.77}, {"Candidate": "UPENDRA", "Party": "Anjaan Aadmi Party", "EVM Votes": 1280, "Postal Votes": 1, "Total Votes": 1281, "Percentage of Votes": 0.14}, {"Candidate": "UMESH CHANDRA GAUR", "Party": "Republican Party of India (A)", "EVM Votes": 284, "Postal Votes": 1, "Total Votes": 285, "Percentage of Votes": 0.03}, {"Candidate": "JITENDRA RAUT", "Party": "Akhil Bharatiya Manavata Paksha", "EVM Votes": 404, "Postal Votes": 1, "Total Votes": 405, "Percentage of Votes": 0.04}, {"Candidate": "NAVEEN KUMAR", "Party": "Rashtriya Samrasta Party", "EVM Votes": 257, "Postal Votes": 0, "Total Votes": 257, "Percentage of Votes": 0.03}, {"Candidate": "NILANJAN BANERJEE", "Party": "Bharat Lok Sewak Party", "EVM Votes": 193, "Postal Votes": 1, "Total Votes": 194, "Percentage of Votes": 0.02}, {"Candidate": "RAVINDER PAUL SEHGAL", "Party": "Pyramid Party of India", "EVM Votes": 323, "Postal Votes": 0, "Total Votes": 323, "Percentage of Votes": 0.04}, {"Candidate": "RAJ KARAN", "Party": "Corruption Abolition Party", "EVM Votes": 275, "Postal Votes": 0, "Total Votes": 275, "Percentage of Votes": 0.03}, {"Candidate": "RAJ SHEKHAR GUNTI", "Party": "Prism", "EVM Votes": 174, "Postal Votes": 0, "Total Votes": 174, "Percentage of Votes": 0.02}, {"Candidate": "RAJESH SATIYA", "Party": "Sanatan Sanskriti Raksha Dal", "EVM Votes": 332, "Postal Votes": 1, "Total Votes": 333, "Percentage of Votes": 0.04}, {"Candidate": "LAL JI", "Party": "Akhand Rashtrawadi Party", "EVM Votes": 307, "Postal Votes": 0, "Total Votes": 307, "Percentage of Votes": 0.03}, {"Candidate": "VIRENDRA SINGH BHARAT", "Party": "Rashtriya Rashtrawadi Party", "EVM Votes": 530, "Postal Votes": 0, "Total Votes": 530, "Percentage of Votes": 0.06}, {"Candidate": "K SREEKRISHNA", "Party": "Jammu & Kashmir National Panthers Party", "EVM Votes": 919, "Postal Votes": 1, "Total Votes": 920, "Percentage of Votes": 0.1}, {"Candidate": "SUNIL", "Party": "Aapki Apni Party (Peoples)", "EVM Votes": 1159, "Postal Votes": 0, "Total Votes": 1159, "Percentage of Votes": 0.13}, {"Candidate": "SUNIL KUMAR", "Party": "Peoples Party of India (Democratic)", "EVM Votes": 1272, "Postal Votes": 0, "Total Votes": 1272, "Percentage of Votes": 0.14}, {"Candidate": "SWADESH KUMAR OHRI", "Party": "Atulya Bharat Party", "EVM Votes": 641, "Postal Votes": 0, "Total Votes": 641, "Percentage of Votes": 0.07}, {"Candidate": "AJAY KUMAR LAL", "Party": "Independent", "EVM Votes": 639, "Postal Votes": 0, "Total Votes": 639, "Percentage of Votes": 0.07}, {"Candidate": "AASHISH S SAXENA", "Party": "Independent", "EVM Votes": 198, "Postal Votes": 0, "Total Votes": 198, "Percentage of Votes": 0.02}, {"Candidate": "KRIPASHANKAR C PANDEY", "Party": "Independent", "EVM Votes": 184, "Postal Votes": 0, "Total Votes": 184, "Percentage of Votes": 0.02}, {"Candidate": "DILIP SINGH KOTHARI", "Party": "Independent", "EVM Votes": 255, "Postal Votes": 0, "Total Votes": 255, "Percentage of Votes": 0.03}, {"Candidate": "PRIYANKA", "Party": "Independent", "EVM Votes": 289, "Postal Votes": 0, "Total Votes": 289, "Percentage of Votes": 0.03}, {"Candidate": "RAMESH", "Party": "Independent", "EVM Votes": 200, "Postal Votes": 0, "Total Votes": 200, "Percentage of Votes": 0.02}, {"Candidate": "SREE NIVASAN RAMAMOORTHY", "Party": "Independent", "EVM Votes": 237, "Postal Votes": 1, "Total Votes": 238, "Percentage of Votes": 0.03}, {"Candidate": "SURESH KUMAR", "Party": "Independent", "EVM Votes": 721, "Postal Votes": 0, "Total Votes": 721, "Percentage of Votes": 0.08}, {"Candidate": "HARKRISHAN DAS NIJHAWAN", "Party": "Independent", "EVM Votes": 609, "Postal Votes": 1, "Total Votes": 610, "Percentage of Votes": 0.07}, {"Candidate": "NOTA", "Party": "None of the Above", "EVM Votes": 6585, "Postal Votes": 16, "Total Votes": 6601, "Percentage of Votes": 0.72}], "Voters": {"EVM Voters": 919056, "Postal Voters": 1485, "Total Voters": 920541}, "Year": 2019}, {"State": "NCT OF Delhi", "PC_Name": "NORTH EAST DELHI", "PC_Number": "2", "Result": [{"Candidate": "DILIP PANDEY", "Party": "Aam Aadmi Party", "EVM Votes": 190586, "Postal Votes": 270, "Total Votes": 190856, "Percentage of Votes": 13.06}, {"Candidate": "MANOJ TIWARI", "Party": "Bharatiya Janata Party", "EVM Votes": 785262, "Postal Votes": 2537, "Total Votes": 787799, "Percentage of Votes": 53.9}, {"Candidate": "RAJVEER SINGH", "Party": "Bahujan Samaj Party", "EVM Votes": 37630, "Postal Votes": 201, "Total Votes": 37831, "Percentage of Votes": 2.59}, {"Candidate": "SHEILA DIKSHIT", "Party": "Indian National Congress", "EVM Votes": 421293, "Postal Votes": 404, "Total Votes": 421697, "Percentage of Votes": 28.85}, {"Candidate": "AJAY BHAI", "Party": "Right to Recall Party", "EVM Votes": 1822, "Postal Votes": 0, "Total Votes": 1822, "Percentage of Votes": 0.12}, {"Candidate": "ANURUDDH KUMAR DUBE", "Party": "Bharat Lok Sewak Party", "EVM Votes": 419, "Postal Votes": 0, "Total Votes": 419, "Percentage of Votes": 0.03}, {"Candidate": "ABHINAV KUMAR", "Party": "Sanyukt Vikas Party", "EVM Votes": 309, "Postal Votes": 0, "Total Votes": 309, "Percentage of Votes": 0.02}, {"Candidate": "AMIT KUMAR SHARMA", "Party": "Sanjhi Virasat Party", "EVM Votes": 419, "Postal Votes": 0, "Total Votes": 419, "Percentage of Votes": 0.03}, {"Candidate": "J. K. JAIN", "Party": "Jai Prakash Janata Dal", "EVM Votes": 456, "Postal Votes": 0, "Total Votes": 456, "Percentage of Votes": 0.03}, {"Candidate": "DAN BAHADUR YADAV", "Party": "Bhartiya Janta Dal (Integrated)", "EVM Votes": 434, "Postal Votes": 1, "Total Votes": 435, "Percentage of Votes": 0.03}, {"Candidate": "D. Durga Prasad", "Party": "Challengers Party", "EVM Votes": 684, "Postal Votes": 0, "Total Votes": 684, "Percentage of Votes": 0.05}, {"Candidate": "PRADESH KUMAR", "Party": "Sarvodaya Prabhat Party", "EVM Votes": 740, "Postal Votes": 0, "Total Votes": 740, "Percentage of Votes": 0.05}, {"Candidate": "MAHENDER PASWAN", "Party": "Mazdoor Kirayedar Vikas Party", "EVM Votes": 792, "Postal Votes": 0, "Total Votes": 792, "Percentage of Votes": 0.05}, {"Candidate": "MUKESH", "Party": "Aapki Apni Party (Peoples)", "EVM Votes": 1472, "Postal Votes": 3, "Total Votes": 1475, "Percentage of Votes": 0.1}, {"Candidate": "MANAGER CHAURASIYA", "Party": "SOCIALIST UNITY CENTRE OF INDIA (COMMUNIST)", "EVM Votes": 1749, "Postal Votes": 0, "Total Votes": 1749, "Percentage of Votes": 0.12}, {"Candidate": "MOHD. IRFAN", "Party": "Bharat Prabhat Party", "EVM Votes": 1746, "Postal Votes": 0, "Total Votes": 1746, "Percentage of Votes": 0.12}, {"Candidate": "SUNIL VISHVAKARMA", "Party": "Ambedkar National Congress", "EVM Votes": 2147, "Postal Votes": 1, "Total Votes": 2148, "Percentage of Votes": 0.15}, {"Candidate": "MOHD. HASAN", "Party": "Republican Party of India (A)", "EVM Votes": 1342, "Postal Votes": 1, "Total Votes": 1343, "Percentage of Votes": 0.09}, {"Candidate": "MD. AKRAM", "Party": "Independent", "EVM Votes": 805, "Postal Votes": 0, "Total Votes": 805, "Percentage of Votes": 0.06}, {"Candidate": "ANIL KUMAR YADAV", "Party": "Independent", "EVM Votes": 1242, "Postal Votes": 0, "Total Votes": 1242, "Percentage of Votes": 0.08}, {"Candidate": "AMRENDER KUMAR", "Party": "Independent", "EVM Votes": 531, "Postal Votes": 0, "Total Votes": 531, "Percentage of Votes": 0.04}, {"Candidate": "MAHFOOZ KHAN", "Party": "Independent", "EVM Votes": 302, "Postal Votes": 0, "Total Votes": 302, "Percentage of Votes": 0.02}, {"Candidate": "YOGESH SWAMY", "Party": "Independent", "EVM Votes": 544, "Postal Votes": 0, "Total Votes": 544, "Percentage of Votes": 0.04}, {"Candidate": "S N SINGH", "Party": "Independent", "EVM Votes": 742, "Postal Votes": 0, "Total Votes": 742, "Percentage of Votes": 0.05}, {"Candidate": "NOTA", "Party": "None of the Above", "EVM Votes": 4578, "Postal Votes": 11, "Total Votes": 4589, "Percentage of Votes": 0.31}], "Voters": {"EVM Voters": 1458046, "Postal Voters": 3429, "Total Voters": 1461475}, "Year": 2019}, {"State": "NCT OF Delhi", "PC_Name": "NORTH WEST DELHI", "PC_Number": "5", "Result": [{"Candidate": "GUGAN SINGH", "Party": "Aam Aadmi Party", "EVM Votes": 294662, "Postal Votes": 104, "Total Votes": 294766, "Percentage of Votes": 21.01}, {"Candidate": "RAJESH LILOTHIA", "Party": "Indian National Congress", "EVM Votes": 236803, "Postal Votes": 79, "Total Votes": 236882, "Percentage of Votes": 16.88}, {"Candidate": "HANS RAJ HANS", "Party": "Bharatiya Janata Party", "EVM Votes": 847737, "Postal Votes": 926, "Total Votes": 848663, "Percentage of Votes": 60.49}, {"Candidate": "ISHWAR MANSUKH ISHU", "Party": "Satya Bahumat Party", "EVM Votes": 2348, "Postal Votes": 0, "Total Votes": 2348, "Percentage of Votes": 0.17}, {"Candidate": "GAURAV BHATIA", "Party": "Mazdoor Kirayedar Vikas Party", "EVM Votes": 874, "Postal Votes": 0, "Total Votes": 874, "Percentage of Votes": 0.06}, {"Candidate": "MADAN LAL BALMIKI", "Party": "Rashtriya Samrasta Party", "EVM Votes": 1175, "Postal Votes": 0, "Total Votes": 1175, "Percentage of Votes": 0.08}, {"Candidate": "RAM KUMAR", "Party": "Bhartiya Pragatisheel Congress", "EVM Votes": 724, "Postal Votes": 0, "Total Votes": 724, "Percentage of Votes": 0.05}, {"Candidate": "SURESH KUMAR", "Party": "Socialist Janata Party", "EVM Votes": 805, "Postal Votes": 0, "Total Votes": 805, "Percentage of Votes": 0.06}, {"Candidate": "ADITI", "Party": "Independent", "EVM Votes": 1464, "Postal Votes": 0, "Total Votes": 1464, "Percentage of Votes": 0.1}, {"Candidate": "CHARAN SINGH \"BABRIK\"", "Party": "Independent", "EVM Votes": 2915, "Postal Votes": 0, "Total Votes": 2915, "Percentage of Votes": 0.21}, {"Candidate": "NAVEEN", "Party": "Independent", "EVM Votes": 2136, "Postal Votes": 0, "Total Votes": 2136, "Percentage of Votes": 0.15}, {"Candidate": "NOTA", "Party": "None of the Above", "EVM Votes": 10199, "Postal Votes": 11, "Total Votes": 10210, "Percentage of Votes": 0.73}], "Voters": {"EVM Voters": 1401842, "Postal Voters": 1120, "Total Voters": 1402962}, "Year": 2019}, {"State": "NCT OF Delhi", "PC_Name": "SOUTH DELHI", "PC_Number": "7", "Result": [{"Candidate": "RAMESH BIDHURI", "Party": "Bharatiya Janata Party", "EVM Votes": 685789, "Postal Votes": 1225, "Total Votes": 687014, "Percentage of Votes": 56.58}, {"Candidate": "RAGHAV CHADHA", "Party": "Aam Aadmi Party", "EVM Votes": 319770, "Postal Votes": 201, "Total Votes": 319971, "Percentage of Votes": 26.35}, {"Candidate": "VIJENDER", "Party": "Indian National Congress", "EVM Votes": 164394, "Postal Votes": 219, "Total Votes": 164613, "Percentage of Votes": 13.56}, {"Candidate": "SIDDHANT GAUTAM", "Party": "Bahujan Samaj Party", "EVM Votes": 14721, "Postal Votes": 40, "Total Votes": 14761, "Percentage of Votes": 1.22}, {"Candidate": "Aditya Kumar Naveen", "Party": "Hum Bhartiya Party", "EVM Votes": 3892, "Postal Votes": 0, "Total Votes": 3892, "Percentage of Votes": 0.32}, {"Candidate": "D. K. CHOPRA", "Party": "All India Forward Bloc", "EVM Votes": 366, "Postal Votes": 1, "Total Votes": 367, "Percentage of Votes": 0.03}, {"Candidate": "JITENDRA SHARMA", "Party": "Prism", "EVM Votes": 200, "Postal Votes": 0, "Total Votes": 200, "Percentage of Votes": 0.02}, {"Candidate": "DALBIR SINGH MALIK", "Party": "Voters Party  International", "EVM Votes": 314, "Postal Votes": 0, "Total Votes": 314, "Percentage of Votes": 0.03}, {"Candidate": "DILIP KUMAR", "Party": "Sanatan Sanskriti Raksha Dal", "EVM Votes": 472, "Postal Votes": 1, "Total Votes": 473, "Percentage of Votes": 0.04}, {"Candidate": "DEEPAK KUMAR", "Party": "Aapki Apni Party (Peoples)", "EVM Votes": 929, "Postal Votes": 0, "Total Votes": 929, "Percentage of Votes": 0.08}, {"Candidate": "DESH KUMAR", "Party": "Akhil Bharatiya Jan Sangh", "EVM Votes": 403, "Postal Votes": 0, "Total Votes": 403, "Percentage of Votes": 0.03}, {"Candidate": "NAVANIT", "Party": "National Youth Party", "EVM Votes": 334, "Postal Votes": 0, "Total Votes": 334, "Percentage of Votes": 0.03}, {"Candidate": "MAHENDER SINGH CHURIYANA", "Party": "Peoples Party of India (Democratic)", "EVM Votes": 1019, "Postal Votes": 0, "Total Votes": 1019, "Percentage of Votes": 0.08}, {"Candidate": "MATHEWS", "Party": "Bhartiya Insan Party", "EVM Votes": 1139, "Postal Votes": 0, "Total Votes": 1139, "Percentage of Votes": 0.09}, {"Candidate": "MOHAN KUMAR GUPTA", "Party": "Mazdoor Kirayedar Vikas Party", "EVM Votes": 969, "Postal Votes": 0, "Total Votes": 969, "Percentage of Votes": 0.08}, {"Candidate": "RAJENDRA PRASAD GUPTA", "Party": "Parivartan Samaj Party", "EVM Votes": 1897, "Postal Votes": 0, "Total Votes": 1897, "Percentage of Votes": 0.16}, {"Candidate": "RAM KHILAWAN", "Party": "Proutist Bloc, India", "EVM Votes": 2541, "Postal Votes": 0, "Total Votes": 2541, "Percentage of Votes": 0.21}, {"Candidate": "K. ROSHAN KUMAR", "Party": "Pyramid Party of India", "EVM Votes": 1399, "Postal Votes": 0, "Total Votes": 1399, "Percentage of Votes": 0.12}, {"Candidate": "SUMAN YADAV", "Party": "Jai Maha Bharath Party", "EVM Votes": 1531, "Postal Votes": 6, "Total Votes": 1537, "Percentage of Votes": 0.13}, {"Candidate": "SUMEDHA BODH", "Party": "Jan Samman party", "EVM Votes": 1708, "Postal Votes": 0, "Total Votes": 1708, "Percentage of Votes": 0.14}, {"Candidate": "SOBRAN SINGH CHAUHAN", "Party": "Rashtriya Rashtrawadi Party", "EVM Votes": 278, "Postal Votes": 0, "Total Votes": 278, "Percentage of Votes": 0.02}, {"Candidate": "SANDEEP GUPTA", "Party": "Rashtriya Jan  Adhikar Party", "EVM Votes": 370, "Postal Votes": 0, "Total Votes": 370, "Percentage of Votes": 0.03}, {"Candidate": "NAUSHA KHAN", "Party": "Independent", "EVM Votes": 214, "Postal Votes": 1, "Total Votes": 215, "Percentage of Votes": 0.02}, {"Candidate": "BIRJU NAYAK", "Party": "Independent", "EVM Votes": 390, "Postal Votes": 0, "Total Votes": 390, "Percentage of Votes": 0.03}, {"Candidate": "ROSHAN KUMAR CHOUDHARY", "Party": "Independent", "EVM Votes": 731, "Postal Votes": 0, "Total Votes": 731, "Percentage of Votes": 0.06}, {"Candidate": "SUNIL KUMAR", "Party": "Independent", "EVM Votes": 390, "Postal Votes": 0, "Total Votes": 390, "Percentage of Votes": 0.03}, {"Candidate": "HARSH NATH VERMA", "Party": "Independent", "EVM Votes": 1104, "Postal Votes": 0, "Total Votes": 1104, "Percentage of Votes": 0.09}, {"Candidate": "NOTA", "Party": "None of the Above", "EVM Votes": 5247, "Postal Votes": 17, "Total Votes": 5264, "Percentage of Votes": 0.43}], "Voters": {"EVM Voters": 1212511, "Postal Voters": 1711, "Total Voters": 1214222}, "Year": 2019}, {"State": "NCT OF Delhi", "PC_Name": "WEST DELHI", "PC_Number": "6", "Result": [{"Candidate": "PARVESH SAHIB SINGH VERMA", "Party": "Bharatiya Janata Party", "EVM Votes": 862058, "Postal Votes": 3590, "Total Votes": 865648, "Percentage of Votes": 60.05}, {"Candidate": "BALBIR SINGH JAKHAR", "Party": "Aam Aadmi Party", "EVM Votes": 251504, "Postal Votes": 369, "Total Votes": 251873, "Percentage of Votes": 17.47}, {"Candidate": "MAHABAL MISHRA", "Party": "Indian National Congress", "EVM Votes": 286745, "Postal Votes": 417, "Total Votes": 287162, "Percentage of Votes": 19.92}, {"Candidate": "SITA SARAN SEN", "Party": "Bahujan Samaj Party", "EVM Votes": 13202, "Postal Votes": 67, "Total Votes": 13269, "Percentage of Votes": 0.92}, {"Candidate": "KULWINDER SINGH MEHTA", "Party": "Pyramid Party of India", "EVM Votes": 542, "Postal Votes": 0, "Total Votes": 542, "Percentage of Votes": 0.04}, {"Candidate": "JANAK RAJ RANA", "Party": "Akhand Rashtrawadi Party", "EVM Votes": 329, "Postal Votes": 0, "Total Votes": 329, "Percentage of Votes": 0.02}, {"Candidate": "DAYA NAND VATS", "Party": "Republican Party of India (A)", "EVM Votes": 379, "Postal Votes": 0, "Total Votes": 379, "Percentage of Votes": 0.03}, {"Candidate": "DHARAMBIR SINGH", "Party": "Rashtriya Janshakti Party (Secular)", "EVM Votes": 551, "Postal Votes": 0, "Total Votes": 551, "Percentage of Votes": 0.04}, {"Candidate": "POONAM UJJAINWAL", "Party": "Peoples Party of India (Democratic)", "EVM Votes": 928, "Postal Votes": 7, "Total Votes": 935, "Percentage of Votes": 0.06}, {"Candidate": "PROBIR DUTTA", "Party": "Satya Bahumat Party", "EVM Votes": 328, "Postal Votes": 1, "Total Votes": 329, "Percentage of Votes": 0.02}, {"Candidate": "BAIDYANATH SAH", "Party": "Proutist Bloc, India", "EVM Votes": 467, "Postal Votes": 0, "Total Votes": 467, "Percentage of Votes": 0.03}, {"Candidate": "MANMOHAN SINGH", "Party": "Rashtra Nirman Party", "EVM Votes": 444, "Postal Votes": 0, "Total Votes": 444, "Percentage of Votes": 0.03}, {"Candidate": "VIKASH KUMAR MOHAL", "Party": "Aapki Apni Party (Peoples)", "EVM Votes": 894, "Postal Votes": 1, "Total Votes": 895, "Percentage of Votes": 0.06}, {"Candidate": "SHASHI JEET", "Party": "National Youth Party", "EVM Votes": 718, "Postal Votes": 1, "Total Votes": 719, "Percentage of Votes": 0.05}, {"Candidate": "SHISH PAL SINGH", "Party": "Prism", "EVM Votes": 538, "Postal Votes": 0, "Total Votes": 538, "Percentage of Votes": 0.04}, {"Candidate": "IQBAL SINGH (SONU)", "Party": "Independent", "EVM Votes": 2181, "Postal Votes": 5, "Total Votes": 2186, "Percentage of Votes": 0.15}, {"Candidate": "NAVIN CHANDRA DAS", "Party": "Independent", "EVM Votes": 1706, "Postal Votes": 0, "Total Votes": 1706, "Percentage of Votes": 0.12}, {"Candidate": "PRAVESH SHARMA", "Party": "Independent", "EVM Votes": 1755, "Postal Votes": 2, "Total Votes": 1757, "Percentage of Votes": 0.12}, {"Candidate": "BALBIR SINGH", "Party": "Independent", "EVM Votes": 1024, "Postal Votes": 0, "Total Votes": 1024, "Percentage of Votes": 0.07}, {"Candidate": "M. MISHRA", "Party": "Independent", "EVM Votes": 652, "Postal Votes": 0, "Total Votes": 652, "Percentage of Votes": 0.05}, {"Candidate": "RAMESH CHAND VERMA", "Party": "Independent", "EVM Votes": 312, "Postal Votes": 0, "Total Votes": 312, "Percentage of Votes": 0.02}, {"Candidate": "RAJIV KUMAR", "Party": "Independent", "EVM Votes": 365, "Postal Votes": 0, "Total Votes": 365, "Percentage of Votes": 0.03}, {"Candidate": "HARSH VARDHAN SHUKLA", "Party": "Independent", "EVM Votes": 582, "Postal Votes": 0, "Total Votes": 582, "Percentage of Votes": 0.04}, {"Candidate": "NOTA", "Party": "None of the Above", "EVM Votes": 8883, "Postal Votes": 54, "Total Votes": 8937, "Percentage of Votes": 0.62}], "Voters": {"EVM Voters": 1437087, "Postal Voters": 4514, "Total Voters": 1441601}, "Year": 2019}]