{"State": "Bihar", "PC_Name": "Siwan", "PC_Number": "18", "Result": [{"Candidate": "Kavita Singh", "Party": "Janata Dal  (United)", "EVM Votes": 447171, "Postal Votes": 1302, "Total Votes": 448473, "Percentage of Votes": 45.54}, {"Candidate": "Balmiki Prasad Gupta", "Party": "Bahujan Samaj Party", "EVM Votes": 8433, "Postal Votes": 34, "Total Votes": 8467, "Percentage of Votes": 0.86}, {"Candidate": "Hena Shahab", "Party": "Rashtriya Janata Dal", "EVM Votes": 330363, "Postal Votes": 1152, "Total Votes": 331515, "Percentage of Votes": 33.66}, {"Candidate": "Amar Nath Yadav", "Party": "Communist Party of India  (Marxist-Leninist)  (Liberation)", "EVM Votes": 74554, "Postal Votes": 90, "Total Votes": 74644, "Percentage of Votes": 7.58}, {"Candidate": "Narad Pandit", "Party": "Bharatiya Samta Samaj Party", "EVM Votes": 3604, "Postal Votes": 11, "Total Votes": 3615, "Percentage of Votes": 0.37}, {"Candidate": "Parmanand Gond", "Party": "Swatantra Samaj Party", "EVM Votes": 2062, "Postal Votes": 7, "Total Votes": 2069, "Percentage of Votes": 0.21}, {"Candidate": "Bijay bahadur Singh", "Party": "Rashtriya Sahyog Party", "EVM Votes": 2754, "Postal Votes": 2, "Total Votes": 2756, "Percentage of Votes": 0.28}, {"Candidate": "Rohit Kumar Yadav", "Party": "Sanyukt Vikas Party", "EVM Votes": 2360, "Postal Votes": 4, "Total Votes": 2364, "Percentage of Votes": 0.24}, {"Candidate": "Shabana", "Party": "Jai Prakash Janata Dal", "EVM Votes": 2103, "Postal Votes": 4, "Total Votes": 2107, "Percentage of Votes": 0.21}, {"Candidate": "Sudhir Kuamr Singh", "Party": "Shivsena", "EVM Votes": 2686, "Postal Votes": 15, "Total Votes": 2701, "Percentage of Votes": 0.27}, {"Candidate": "Anil Kumar Verma", "Party": "Independent", "EVM Votes": 5260, "Postal Votes": 0, "Total Votes": 5260, "Percentage of Votes": 0.53}, {"Candidate": "Abhishek Kumar Alias Rinku Ji", "Party": "Independent", "EVM Votes": 3573, "Postal Votes": 0, "Total Votes": 3573, "Percentage of Votes": 0.36}, {"Candidate": "Amarjit Prasad", "Party": "Independent", "EVM Votes": 7668, "Postal Votes": 3, "Total Votes": 7671, "Percentage of Votes": 0.78}, {"Candidate": "Upendra Kumar Giri", "Party": "Independent", "EVM Votes": 17352, "Postal Votes": 1, "Total Votes": 17353, "Percentage of Votes": 1.76}, {"Candidate": "Jai Prakash Prasad Alias J.P.Bhai", "Party": "Independent", "EVM Votes": 5964, "Postal Votes": 0, "Total Votes": 5964, "Percentage of Votes": 0.61}, {"Candidate": "Deva Kant Mishra Alias Munna Bhaiya", "Party": "Independent", "EVM Votes": 36458, "Postal Votes": 1, "Total Votes": 36459, "Percentage of Votes": 3.7}, {"Candidate": "Madhuri Pandey", "Party": "Independent", "EVM Votes": 12927, "Postal Votes": 1, "Total Votes": 12928, "Percentage of Votes": 1.31}, {"Candidate": "Sanjay Prajapatee", "Party": "Independent", "EVM Votes": 2352, "Postal Votes": 2, "Total Votes": 2354, "Percentage of Votes": 0.24}, {"Candidate": "Satyendra Kushwaha", "Party": "Independent", "EVM Votes": 6043, "Postal Votes": 8, "Total Votes": 6051, "Percentage of Votes": 0.61}, {"Candidate": "NOTA", "Party": "None of the Above", "EVM Votes": 8464, "Postal Votes": 22, "Total Votes": 8486, "Percentage of Votes": 0.86}], "Voters": {"EVM Voters": 982151, "Postal Voters": 2659, "Total Voters": 984810}, "Year": 2019}